structify/__init__.py
structify/_structify.py
structify/_version.py
structify/py.typed
struuuctify-0.0.4.dist-info/METADATA
struuuctify-0.0.4.dist-info/WHEEL
struuuctify-0.0.4.dist-info/licenses/LICENSE
struuuctify-0.0.4.dist-info/RECORD
