Metadata-Version: 2.3
Name: struuuctify
Version: 0.0.4
Project-URL: Homepage, https://github.com/halbow/structify
Project-URL: Bug Tracker, https://github.com/halbow/structify/issues
Author: halbow
License-File: LICENSE
Classifier: License :: OSI Approved :: MIT License
Classifier: Operating System :: OS Independent
Classifier: Programming Language :: Python :: 3
Classifier: Typing :: Typed
Requires-Python: >=3.11
Provides-Extra: dev
Requires-Dist: mypy; extra == 'dev'
Requires-Dist: pytest; extra == 'dev'
Requires-Dist: pytest-cov; extra == 'dev'
Requires-Dist: ruff; extra == 'dev'
